[
  {
    "domain": "健康管理",
    "model": [
      {
        "name": "预防思维",
        "info": "通过前瞻性行为降低健康风险，强调疫苗接种、定期体检、合理膳食和运动等主动预防措施，建立疾病发生前的防御体系。"
      },
      {
        "name": "循证医学模型",
        "info": "整合最佳临床证据、个人经验和患者价值观进行医疗决策，要求健康干预手段必须通过随机对照试验等科学验证。"
      },
      {
        "name": "生物-心理-社会模型",
        "info": "从生物学特征、心理状态、社会环境三个维度综合分析健康问题，制定包含药物治疗、心理干预、环境调整的综合解决方案。"
      },
      {
        "name": "代谢平衡法则",
        "info": "通过监测基础代谢率、体脂率等指标建立能量守恒方程，采用量化饮食记录与运动追踪实现精准的体重管理。"
      },
      {
        "name": "昼夜节律调控",
        "info": "根据人体24小时生物钟规律安排作息，利用光照管理、褪黑素调控等方法解决睡眠障碍，保持内分泌系统正常节律。"
      }
    ]
  },
  {
    "domain": "决策制定",
    "model": [
      {
        "name": "SWOT分析框架",
        "info": "系统性评估决策选项的优势(Strengths)、劣势(Weaknesses)、机会(Opportunities)和威胁(Threats)，通过四象限矩阵进行可视化呈现，要求列出每个维度的具体事实依据并建立关联性分析。"
      },
      {
        "name": "成本效益分析",
        "info": "将决策选项转化为可量化的成本与收益指标，建立时间维度模型计算净现值，需包含显性/隐性成本、直接/间接收益及机会成本的系统核算方法。"
      },
      {
        "name": "决策树模型",
        "info": "用树状图表示多阶段决策过程，要求标注每个节点的预期值、概率分支及终止条件，运用贝叶斯定理动态更新概率估计，包含敏感性分析环节。"
      },
      {
        "name": "贝叶斯思维模型",
        "info": "建立先验概率假设，通过新证据输入持续更新后验概率的计算框架，要求明确证据权重赋值规则和条件独立性的验证方法。"
      },
      {
        "name": "双回路学习系统",
        "info": "在决策执行过程中同步进行结果反馈（单回路学习）和决策框架检验（双回路学习），包含认知偏差检查清单和心智模式迭代升级机制。"
      }
    ]
  },
  {
    "domain": "项目管理",
    "model": [
      {
        "name": "关键路径法",
        "info": "通过识别项目中时间最长的任务序列来确定最短完成时间，明确任务间依赖关系与浮动时间，用于优化进度安排和资源分配。具体步骤包括列出所有任务、估算持续时间、确定依赖关系、绘制网络图并计算关键路径。"
      },
      {
        "name": "敏捷冲刺规划",
        "info": "将项目分解为2-4周的迭代周期，在冲刺开始时确定可实现的目标，通过每日站会跟踪进展，冲刺结束时进行成果演示和回顾改进。要求团队具备快速响应需求变化的能力，适用于需求不明确或易变动的项目。"
      },
      {
        "name": "风险矩阵评估",
        "info": "通过两个维度（发生概率x影响程度）量化项目风险，将风险分为红/黄/绿三个区域。对高风险区采取规避/转移策略，中风险区实施缓解措施，低风险区进行持续监控。需定期更新风险登记册并制定应急计划。"
      },
      {
        "name": "SWOT行动矩阵",
        "info": "结合内部优势(Strengths)/劣势(Weaknesses)与外部机会(Opportunities)/威胁(Threats)，形成SO(优势+机会)、WO(劣势+机会)、ST(优势+威胁)、WT(劣势+威胁)四个策略象限，为项目制定攻防兼备的战略方案。"
      },
      {
        "name": "帕累托优先级矩阵",
        "info": "运用80/20法则识别产生80%效果的关键20%任务，结合影响力和实施难度两个维度建立四象限模型。优先处理高影响低难度任务，系统规划高影响高难度任务，批量处理低影响低难度任务，剔除低影响高难度任务。"
      }
    ]
  },
  {
    "domain": "冲突解决",
    "model": [
      {
        "name": "托马斯-基尔曼冲突模式仪",
        "info": "通过竞争/合作/妥协/回避/迁就五个维度评估最佳冲突解决策略，根据事件重要性和关系重要性建立2x2矩阵选择对应模式，需配合换位思考识别对方立场优先级"
      },
      {
        "name": "非暴力沟通四要素",
        "info": "观察(陈述客观事实)→感受(表达真实情绪)→需求(明确核心诉求)→请求(提出具体行动)，要求区分事实与评判，使用'我'句式避免指责，适用于化解情绪化对抗"
      },
      {
        "name": "三层立场分析法",
        "info": "将冲突分解为表面立场(具体要求)→深层利益(核心诉求)→根本需求(心理/安全需求)，通过逐层剥离寻找可替代解决方案，需运用积极倾听和提问技术"
      },
      {
        "name": "共识构建七步法",
        "info": "定义问题→收集观点→识别共同点→澄清分歧→生成选项→评估方案→制定协议，关键在第三步用维恩图可视化共识区，第五步采用头脑风暴暂缓评判"
      }
    ]
  },
  {
    "domain": "投资理财",
    "model": [
      {
        "name": "复利效应",
        "info": "通过持续将投资收益再投资，实现本金与累积收益共同产生新收益的思维模型。需关注时间跨度（建议10年以上）、稳定回报率（年化7%-15%）和定期追加本金三个核心要素。"
      },
      {
        "name": "风险分散原则",
        "info": "通过将资金分配在不同资产类别（股票40%、债券30%、不动产20%、现金10%）、不同行业（科技/消费/医疗等）和不同地域市场，降低单一投资标的带来的风险敞口。"
      },
      {
        "name": "机会成本评估",
        "info": "在选择投资标的时，需要系统比较不同选项的潜在收益（预期年化收益率）、风险系数（波动率）和流动性（变现能力），建立包含机会成本计算的决策矩阵。"
      },
      {
        "name": "边际效用递减",
        "info": "当某类资产配置超过总资产30%时，其风险抵御能力开始下降。建议采用动态再平衡策略，每季度评估并调整持仓比例至预设目标区间。"
      },
      {
        "name": "逆向投资思维",
        "info": "运用市场情绪指标（恐慌指数>40时买入，贪婪指数>80时卖出），结合基本面分析（PE/PB/ROE等指标），在群体非理性时期进行反向操作。"
      }
    ]
  },
  {
    "domain": "创意生成",
    "model": [
      {
        "name": "SCAMPER法",
        "info": "通过替代、结合、调整、修改、转换、消除、逆向七种策略系统化改进现有事物的方法。具体应用时依次对目标对象进行：替代材料/元素，结合功能/场景，调整尺寸/参数，修改外观/结构，转换用途/视角，消除冗余部分，逆向操作流程等七个维度的改造思考。"
      },
      {
        "name": "六顶思考帽",
        "info": "通过角色化平行思维工具提升创意质量，包含：白帽（收集事实数据）、红帽（直觉情感判断）、黑帽（风险预警分析）、黄帽（价值优势发现）、绿帽（创新方案生成）、蓝帽（流程控制管理）。每个思考阶段团队统一佩戴特定颜色帽子进行定向思考，避免思维混乱。"
      },
      {
        "name": "思维导图辐射法",
        "info": "以核心概念为中心节点，通过自由联想生成多层次关联分支的可视化工具。操作步骤：1. 中央放置主题图像 2. 主分支标注关键维度 3. 次级分支展开具体内容 4. 使用颜色/图标强化记忆 5. 建立跨分支连接线 6. 定期迭代更新结构。适用于知识整理与灵感激发。"
      },
      {
        "name": "德尔菲迭代法",
        "info": "通过多轮匿名专家反馈达成创意共识的方法。实施流程：1. 组建跨领域专家组 2. 首轮开放式问题征询 3. 匿名整理反馈报告 4. 次轮针对性深化提问 5. 重复迭代直至收敛 6. 形成最终解决方案。特别适用于复杂系统创新设计。"
      },
      {
        "name": "TRIZ矛盾矩阵",
        "info": "基于专利分析总结的40条发明原理，通过矛盾参数索引对应解决方案的工具。使用步骤：1. 明确技术矛盾中的改善参数与恶化参数 2. 查矩阵表获得推荐原理编号 3. 应用对应原理（如分割、抽取、局部质量等）生成具体方案。"
      }
    ]
  },
  {
    "domain": "习惯养成",
    "model": [
      {
        "name": "习惯回路模型",
        "info": "由暗示-惯常行为-奖励三要素构成的行为循环系统。通过识别触发行为的暗示（如时间/地点/情绪），设计可替代的积极惯常行为，并设置即时奖励机制（如成就感/物质奖励）来重塑习惯。应用时需保持暗示和奖励不变，仅替换中间行为环节。"
      },
      {
        "name": "最小努力原则",
        "info": "通过降低新习惯的启动难度来提升执行率。将目标行为拆解为2分钟可完成的微习惯（如「做1个俯卧撑」代替健身计划），利用行为启动后的持续惯性达成完整目标。重点在于建立行为模式而非初始强度。"
      },
      {
        "name": "行为设计模型",
        "info": "B=MAP公式：行为(Behavior)=动机(Motivation)+能力(Ability)+提示(Prompt)。同时满足三个要素时行为才会发生。可通过提升动机（价值可视化）、降低难度（分解步骤）、设置触发提示（环境线索）的系统方法培养新习惯。"
      },
      {
        "name": "承诺机制",
        "info": "通过预先承诺策略增强行为约束力，包括社会承诺（公开承诺）、财务承诺（押金制度）、物理承诺（移除干扰源）等。利用损失厌恶心理，设置违约成本高于行动成本，促使持续行为保持。"
      }
    ]
  },
  {
    "domain": "用户体验设计",
    "model": [
      {
        "name": "双钻模型",
        "info": "将设计过程分为发散(发现问题)和收敛(定义问题)、再发散(构思方案)和收敛(实施方案)四个阶段，通过两次发散-收敛循环确保问题准确定义与方案有效落实。"
      },
      {
        "name": "雅各布定律",
        "info": "用户将大部分时间花在其他产品上，因此会期望你的产品与已有使用体验保持一致。遵循行业通用交互模式可显著降低用户学习成本。"
      },
      {
        "name": "希克定律",
        "info": "用户面临的选择数量和决策时间呈对数关系。通过合理归类信息、分步骤展示选项、设置默认值等方法，可有效降低用户认知负荷。"
      },
      {
        "name": "费茨定律",
        "info": "点击目标所需时间与目标距离当前位置的距离成正比，与目标尺寸成反比。设计交互元素时应保证高频操作控件足够大且位于易触达区域。"
      },
      {
        "name": "多尔蒂阈值",
        "info": "系统响应时间需在400ms以内才能保持用户流畅的操作节奏，超过此时间需提供加载反馈。即时响应可显著提升用户满意度与操作效率。"
      }
    ]
  },
  {
    "domain": "沟通效能",
    "model": [
      {
        "name": "主动倾听",
        "info": "通过全神贯注、反馈式回应和提问确认三个步骤，确保准确理解对方意图。具体实施时需保持眼神接触，用\"你刚才说...\"句式复述，并以\"我理解对吗？\"结尾请求确认，消除信息偏差。"
      },
      {
        "name": "非暴力沟通四要素",
        "info": "包含观察（陈述具体行为事实）、感受（表达自身情绪）、需求（说明内在动机）、请求（提出可操作建议）的沟通框架。如：\"当会议迟到30分钟（观察），我感到被忽视（感受），因为守时对我很重要（需求），下次能否提前通知？（请求）\""
      },
      {
        "name": "反馈三明治法则",
        "info": "给予反馈时采用积极-改进-积极的三层结构：首先肯定对方优点（\"方案逻辑很清晰\"），然后提出具体改进建议（\"若增加数据支撑会更完整\"），最后以鼓励结尾（\"这个方向很有潜力\"），使建议更易被接受。"
      },
      {
        "name": "5W1H信息澄清法",
        "info": "通过连续追问What（何事）、Why（何因）、When（何时）、Where（何地）、Who（何人）、How（如何）六个维度，系统性地梳理模糊信息。例如处理客户投诉时，依次确认问题表现、发生原因、时间节点、具体场景、责任主体和解决预期。"
      },
      {
        "name": "情感账户理论",
        "info": "将人际关系比作银行账户，通过真诚赞美（存款）、过度索取（取款）等行为积累或消耗信任资本。维护时需保持5:1的积极互动比例，即每提出1次要求前，先进行5次正面沟通建立情感储备。"
      },
      {
        "name": "电梯演讲原则",
        "info": "在30秒内用三层结构清晰表达观点：钩子（吸引注意的事实/问题）、主张（核心观点）、证据（数据/案例支撑）。例如：\"客户流失率上升15%（钩子），我们需要优化服务体系（主张），数据显示响应速度提升后留存率提高20%（证据）\"。"
      }
    ]
  },
  {
    "domain": "时间管理",
    "model": [
      {
        "name": "艾森豪威尔矩阵",
        "info": "将任务按紧急性和重要性分为四个象限：1.紧急且重要（立即处理）2.重要不紧急（计划处理）3.紧急不重要（委托他人）4.不紧急不重要（减少或消除），通过分类优先处理高价值事务。"
      },
      {
        "name": "帕金森定律",
        "info": "通过设定明确的时间限制来对抗工作会自动膨胀占满可用时间的现象，例如使用倒计时法，为每个任务设置合理的截止期限以提高效率。"
      },
      {
        "name": "时间分块法",
        "info": "将工作日划分为专注区块（90分钟深度工作）、缓冲区块（处理临时事务）和休息区块（完全放松），通过番茄钟技术（25分钟工作+5分钟休息循环）保持注意力节奏。"
      },
      {
        "name": "两分钟原则",
        "info": "遇到可在两分钟内完成的任务立即执行，避免小事堆积形成心理负担，同时建立『完成-奖励』的正向循环机制提升行动力。"
      }
    ]
  },
  {
    "domain": "谈判技巧",
    "model": [
      {
        "name": "BATNA（最佳替代方案）",
        "info": "通过预先确定谈判失败时的最佳替代方案来增强谈判地位。具体步骤：1. 列出所有可能的替代方案 2. 评估每个方案的可行性 3. 选择最具价值的方案作为底线。该方法帮助谈判者避免接受不利条款，同时提供客观标准评估谈判进展。"
      },
      {
        "name": "锚定效应应用",
        "info": "利用首个数字报价影响后续谈判范围。操作方式：1. 准备充分数据支撑初始报价 2. 率先提出略高于/低于预期的锚点 3. 通过渐进式调整引导对方思维。需配合合理理由说明锚点正当性，同时保留弹性调整空间。"
      },
      {
        "name": "利益层次分析法",
        "info": "将表面立场（具体要求）与深层需求（根本动机）分离的技术。实施步骤：1. 用5Why分析法追问需求本质 2. 绘制双方利益图谱 3. 寻找可交换的非竞争性利益。适用于突破僵局，创造价值增值型协议。"
      },
      {
        "name": "战略同理心",
        "info": "通过主动倾听和镜像反射技术建立信任。关键要素：1. 标注对方情绪状态（\"听起来您对...很重视\"）2. 校准式提问（\"是什么让这个条件如此重要？\"）3. 战术沉默引导对方透露信息。需保持中立立场避免价值判断。"
      }
    ]
  },
  {
    "domain": "气候变化应对",
    "model": [
      {
        "name": "系统思维模型",
        "info": "通过识别大气、海洋、生物圈和人类活动的相互作用网络，建立气候系统各要素的因果反馈循环，用于预测政策干预的连锁反应和长期影响。"
      },
      {
        "name": "弹性思维框架",
        "info": "重点分析生态系统和社会系统的恢复能力，通过冗余设计、模块化结构和多样性维持，帮助社区在极端天气事件后重建关键功能。"
      },
      {
        "name": "预防原则模型",
        "info": "在存在重大或不可逆损害威胁时，即使科学证据尚未完全确立，也应优先采取成本可控的预防措施，特别适用于新型气候技术的风险评估。"
      },
      {
        "name": "减缓-适应双轨策略",
        "info": "将温室气体减排措施（减缓）与提升抗灾能力建设（适应）作为并行解决方案，通过协同效应矩阵评估不同组合方案的综合效益。"
      },
      {
        "name": "利益相关者参与模型",
        "info": "运用多利益方协商平台，整合政府、企业、原住民和科研机构的气候认知，通过利益映射工具平衡减排目标与社会公平需求。"
      }
    ]
  },
  {
    "domain": "职业发展",
    "model": [
      {
        "name": "SWOT自我分析",
        "info": "系统性评估个人职业发展的内部优势(Strengths)、劣势(Weaknesses)及外部机会(Opportunities)、威胁(Threats)。操作步骤：列出四象限表格，将能力、资源填入优势栏，技能短板填劣势栏，行业趋势填入机会栏，竞争压力填威胁栏，通过交叉分析制定职业策略。"
      },
      {
        "name": "成长型思维模型",
        "info": "斯坦福Dweck教授提出，认为能力可通过努力发展。应用方法：将职业挑战视为学习机会，用'暂时未能'替代'无法做到'，建立能力发展清单，定期记录技能增长证据，构建可验证的进步轨迹。"
      },
      {
        "name": "双因素理论",
        "info": "赫茨伯格提出的激励-保健理论。职业应用：区分激励因素（成就、成长）与保健因素（薪资、环境），优先确保保健因素达标后，通过承担挑战性项目、获取及时反馈、建立成就档案等方式提升职业满意度。"
      },
      {
        "name": "职业画布模型",
        "info": "可视化工具，包含9个模块：核心资源（技能/经验）、关键活动、价值主张、人际关系、客户群体（雇主/客户）、渠道通路、成本结构、收入来源。使用方法：用便利贴动态调整各模块要素，寻找最优职业组合。"
      },
      {
        "name": "三圈理论",
        "info": "吉姆·柯林斯提出，通过交集定位理想职业：1.列出擅长领域（通过能力测评确认）2.标记有热情的方向（记录心流时刻）3.标注经济价值区（行业薪酬数据）。在三圈重叠区优先发展，单圈区作为过渡选择。"
      }
    ]
  },
  {
    "domain": "复杂问题解决",
    "model": [
      {
        "name": "系统动力学",
        "info": "通过识别系统内各要素的因果关系和反馈循环来分析复杂系统行为的框架。具体步骤：1.绘制因果回路图识别正/负反馈环 2.寻找系统延迟和瓶颈 3.建立存量-流量模型 4.模拟不同干预策略的长期影响。适用于城市规划、组织变革等非线性问题。"
      },
      {
        "name": "分形思维",
        "info": "在不同尺度上寻找重复模式来理解复杂系统的方法论。实施步骤：1.分解问题到不同层次 2.寻找微观与宏观的相似结构 3.建立跨尺度的类比关系 4.通过局部迭代推导整体规律。可用于解决市场演化、生态网络等自相似性问题。"
      },
      {
        "name": "对抗性协作",
        "info": "通过结构化辩论整合对立观点的决策技术。操作流程：1.明确争议焦点 2.组建立场对立的专家小组 3.共同制定验证实验 4.联合解释矛盾证据 5.迭代达成共识。特别适用于处理科学争议和技术伦理困境。"
      }
    ]
  },
  {
    "domain": "公共演讲",
    "model": [
      {
        "name": "金字塔原理",
        "info": "由Barbara Minto提出的结构化表达方法，主张从核心结论出发，逐层展开支持论点。具体步骤：1) 明确中心思想 2) 用MECE法则分解子论点 3) 用SCQA模型(情境-冲突-问题-答案)组织内容。可确保演讲逻辑清晰，层次分明，听众能快速抓住重点。"
      },
      {
        "name": "故事弧线模型",
        "info": "借鉴经典叙事结构设计演讲框架：1) Hook(吸引点)建立连接 2) Rising Action(递进事件)制造张力 3) Climax(高潮)传递核心价值 4) Resolution(收尾)给出行动号召。每个环节需包含具体场景描述和情感共鸣点，适用于TED式演讲设计。"
      },
      {
        "name": "镜像神经元应用",
        "info": "利用神经科学原理增强说服力：1) 刻意模仿听众的肢体语言和语调建立亲和力 2) 用隐喻激活大脑联想区域 3) 设计重复节奏增强记忆点(每7分钟重复核心信息) 4) 加入具身认知元素(如手势引导想象)。需配合60-30-10法则：60%内容逻辑，30%情感共鸣，10%意外惊喜。"
      }
    ]
  },
  {
    "domain": "数据分析",
    "model": [
      {
        "name": "数据驱动决策框架",
        "info": "通过建立数据收集→清洗处理→模式识别→洞见提炼→决策实施的完整链路，将原始数据转化为可执行策略。要求建立关键指标系统(KPI)，使用可视化工具发现趋势，并通过A/B测试验证假设。"
      },
      {
        "name": "统计因果推断模型",
        "info": "运用反事实推理框架，通过随机对照实验/RCT、双重差分法/DID、断点回归/RD等方法区分相关性与因果性。需构建因果图明确变量关系，控制混杂因素，使用工具变量解决内生性问题。"
      },
      {
        "name": "贝叶斯更新机制",
        "info": "基于先验概率分布，通过持续输入新证据动态修正认知的迭代过程。计算公式为：后验概率 = (似然度 × 先验概率)/证据因子。要求建立概率思维，量化不确定性，持续用新数据校准模型。"
      },
      {
        "name": "维度下钻分析法",
        "info": "从宏观指标异常出发，通过时间/空间/用户分层/行为路径等多维度拆解，结合漏斗分析和同期群对比，定位问题根源。需掌握OLAP立方体操作，配合桑基图等可视化工具追踪数据流向。"
      },
      {
        "name": "异常检测四象限法",
        "info": "将数据点按业务影响程度和发生概率分为四个象限：高影响高概率（优先处理）、高影响低概率（建立预警）、低影响高概率（系统优化）、低影响低概率（持续监控）。需结合3σ原则和箱线图进行阈值设定。"
      }
    ]
  },
  {
    "domain": "危机管理",
    "model": [
      {
        "name": "SWOT危机分析框架",
        "info": "通过系统性评估组织内部优势(Strength)、劣势(Weakness)与外部机会(Opportunity)、威胁(Threat)的矩阵模型，帮助识别潜在危机诱因并建立预警指标。具体实施步骤：1)组建跨部门团队进行要素列举 2)构建2x2矩阵交叉分析 3)针对高风险象限制定预防方案 4)建立动态监测机制。"
      },
      {
        "name": "事前验尸法",
        "info": "在危机发生前逆向推演的系统方法：1)假设组织已发生重大危机事件 2)组建独立团队追溯导致崩溃的关键节点 3)分析每个节点可能的预警信号 4)建立三层防御机制（预防/监测/应急）。该方法可有效暴露系统脆弱性，典型案例包括NASA在航天飞机项目中的应用。"
      },
      {
        "name": "压力测试模型",
        "info": "通过构建极端情景模拟系统承受能力的工具：1)定义关键性能指标（如供应链中断天数） 2)设计压力情景（包括灰天鹅事件） 3)建立量化评估模型 4)进行临界点测试 5)制定弹性增强方案。金融机构常用此方法测试资本充足率，同样适用于企业运营风险评估。"
      }
    ]
  },
  {
    "domain": "可持续农业",
    "model": [
      {
        "name": "生态循环思维",
        "info": "将农业生产视为闭合循环系统，通过作物轮作、有机堆肥、生物质能利用等手段实现资源再生，例如用秸秆还田替代化肥，用禽畜粪便生产沼气等具体实施方案。"
      },
      {
        "name": "生物多样性优化",
        "info": "通过间作套种、生态廊道建设、天敌引入等方法构建多样化生态系统，具体操作如玉米与豆类套种固氮，果园放养食虫鸟类控制害虫数量等可执行方案。"
      },
      {
        "name": "土壤健康优先级",
        "info": "采用免耕覆盖、绿肥种植、微生物菌剂等手段改善土壤结构，例如在休耕期种植紫云英作为绿肥，使用蚯蚓塔改善土壤通气性等具体技术措施。"
      },
      {
        "name": "综合虫害管理",
        "info": "结合生物防治（释放寄生蜂）、物理防治（诱虫灯）、化学防治（靶向用药）的三级防控体系，制定监测预警阈值和干预流程图。"
      },
      {
        "name": "气候适应性种植",
        "info": "建立作物选择矩阵模型，综合积温需求、抗旱指数、降水匹配度等参数，制定品种更替路线图及配套栽培技术规程。"
      }
    ]
  },
  {
    "domain": "行为改变",
    "model": [
      {
        "name": "福格行为模型",
        "info": "行为发生需同时具备动机、能力与提示三要素。应用时需降低行为难度（能力），增强触发信号（提示），并匹配用户核心动机（如愉悦/恐惧）。例如设计健身习惯时，将运动装备放在显眼位置（提示），选择10分钟家庭训练（降低能力门槛），关联减脂后自信提升（动机）。"
      },
      {
        "name": "阶段变化理论",
        "info": "将行为改变分为前沉思（未发现问题）、沉思（意识到问题）、准备（计划行动）、行动（实施改变）、维持（巩固成果）五个阶段。干预策略需匹配当前阶段：对前沉思期人群应提高认知，准备期需提供具体工具，维持期需建立防复机制。如戒烟辅导中，对沉思期着重健康风险教育，准备期提供尼古丁替代方案。"
      },
      {
        "name": "助推理论",
        "info": "通过选择架构设计引导自发改变。关键方法包括：默认选项设置（如自动加入器官捐献）、损失厌恶运用（显示能耗对比损失）、简化选择流程（健康餐预包装）。例如在环保领域，将打印机默认设置为双面打印并显示节约纸张数量，比强制规定更有效。"
      }
    ]
  },
  {
    "domain": "信息整合",
    "model": [
      {
        "name": "梅特卡夫定律",
        "info": "将信息节点视作网络中的连接点，信息价值随节点数量呈指数级增长。应用时建立信息关联图谱，通过连接离散数据点发现潜在模式，用网络效应提升信息利用率。"
      },
      {
        "name": "DIKW金字塔",
        "info": "数据(Data)→信息(Information)→知识(Knowledge)→智慧(Wisdom)的递进模型。处理信息时先做数据清洗，转化为结构化信息，通过模式识别提取知识，最终结合上下文形成决策智慧。"
      },
      {
        "name": "信息熵评估",
        "info": "借鉴香农信息论，用熵值衡量信息不确定性。高熵信息需优先验证和结构化处理，低熵信息可直接应用。通过计算信息源的信噪比决定投入的处理资源比例。"
      },
      {
        "name": "敏捷整合",
        "info": "采用迭代式信息处理：1)快速抓取最小信息集 2)建立初步框架 3)验证关键节点 4)循环补充细化。每个迭代周期控制在24-72小时，保持信息处理敏捷性。"
      },
      {
        "name": "林迪效应",
        "info": "优先整合经时间验证的信息源，信息价值与其存活时间成正比。对于新信息采用沙盒隔离处理，建立3个月观察期后再决定是否纳入核心知识体系。"
      }
    ]
  },
  {
    "domain": "风险管理",
    "model": [
      {
        "name": "风险矩阵",
        "info": "通过建立可能性与影响程度的二维坐标，将风险划分为四个象限（高可能性/高影响、高可能性/低影响、低可能性/高影响、低可能性/低影响），优先处理高可能性且高影响的风险，针对不同象限制定差异化应对策略。"
      },
      {
        "name": "黑天鹅理论",
        "info": "由纳西姆·塔勒布提出，重点关注具有极大冲击性、事后可解释性但事前难以预测的极端事件。应用方法包括：建立冗余系统、避免过度优化、保持反脆弱性（从波动中获益）、对预测保持怀疑态度。"
      },
      {
        "name": "贝叶斯更新",
        "info": "通过持续收集新证据，动态调整风险概率估计值。具体步骤：建立先验概率→定义似然函数→获取新数据→计算后验概率。适用于需要持续监控演化的风险场景，如金融市场波动或疫情传播。"
      },
      {
        "name": "FMEA失效模式分析",
        "info": "系统识别流程中的潜在故障点，评估故障严重度(S)、发生频度(O)、检测难度(D)三个维度，计算风险优先数RPN=S×O×D。针对RPN值高的失效模式，优先实施预防措施和应急预案设计。"
      }
    ]
  },
  {
    "domain": "个人成长",
    "model": [
      {
        "name": "成长型思维模型",
        "info": "基于Carol Dweck理论，认为能力可通过努力持续发展。应用方法：将挑战视为学习机会，用'尚未掌握'替代'无法做到'，建立错误分析机制，通过设定学习目标（而非表现目标）推动进步。"
      },
      {
        "name": "反思实践循环",
        "info": "Donald Schön提出的'行动-反思'框架。执行三步骤：1.记录关键事件细节 2.多角度分析成败因素 3.建立改进清单。建议每周固定时间进行结构化复盘，配合KPTP日志法（Keep/Problem/Try/Plan）提升效果。"
      },
      {
        "name": "刻意练习体系",
        "info": "Anders Ericsson提出的专家培养模式。实施要点：分解复杂技能为微能力单元，每个单元设置明确指标；获取即时专业反馈（建议使用3:1正负反馈比）；在85%成功率的挑战区重复训练，配合间隔重复法强化神经回路。"
      },
      {
        "name": "能量管理矩阵",
        "info": "基于Tony Schwartz的能量四象限：身体/情绪/思维/精神能量。优化策略：建立昼夜节律适配的工作周期（如90分钟专注+20分钟恢复），通过情绪标签法管理状态，设置意义锚点维持内在动机。"
      }
    ]
  },
  {
    "domain": "系统优化",
    "model": [
      {
        "name": "瓶颈分析",
        "info": "基于约束理论(TOC)，通过持续识别和改善系统中最薄弱的限制环节来提升整体效率。具体步骤：1) 定位系统瓶颈 2) 最大化瓶颈利用率 3) 使其他环节服从瓶颈节奏 4) 提升瓶颈能力 5) 重复优化新瓶颈"
      },
      {
        "name": "边际效益递减",
        "info": "当某要素持续增加投入时，单位投入带来的效益增量会逐步降低。应用原则：1) 识别投入产出曲线拐点 2) 建立动态监测指标 3) 在边际成本=边际收益时停止投入 4) 将释放的资源转向其他高效益领域"
      },
      {
        "name": "反馈循环",
        "info": "通过建立监测-分析-调整的闭环机制实现系统持续改进。关键要素：1) 定义关键性能指标(KPI) 2) 设置检测频率 3) 建立偏差阈值 4) 设计矫正措施 5) 区分正反馈（增强循环）与负反馈（平衡循环）的交互作用"
      },
      {
        "name": "帕累托法则",
        "info": "识别系统中20%的关键要素产生80%结果的规律。操作步骤：1) 量化各要素贡献度 2) 绘制累积分布曲线 3) 聚焦改进头部20%高影响力要素 4) 对尾部80%低效要素进行标准化/自动化处理"
      }
    ]
  },
  {
    "domain": "可持续城市规划",
    "model": [
      {
        "name": "系统思维",
        "info": "通过识别交通网络、能源系统、水资源管理和社区需求的相互依存关系，预测政策调整对城市生态系统的连锁反应。例如规划自行车道时需同步考虑公共交通接驳、商业分布和排水系统承载力。"
      },
      {
        "name": "15分钟城市模型",
        "info": "确保居民在步行/骑行15分钟内满足工作、教育、医疗、购物等基本需求。实施时需通过地理信息系统(GIS)分析设施分布缺口，结合混合用地政策引导功能复合开发。"
      },
      {
        "name": "海绵城市框架",
        "info": "运用透水铺装、雨水花园、生态湿地等蓝色-绿色基础设施，使城市像海绵般吸收70%以上降雨。需计算百年一遇暴雨强度，设计地表径流引导系统，同步解决内涝与水资源回用问题。"
      },
      {
        "name": "TOD开发模式",
        "info": "以轨道交通站点为中心，800米半径内建设高密度混合社区。规划时需建立车站客流量预测模型，配置梯度容积率（核心区4.0以上，外围逐步递减），预留步行廊道衔接居住与商业功能。"
      },
      {
        "name": "气候适应性设计",
        "info": "结合本地RCP8.5气候情景预测，在建筑规范中强制要求抗台风结构、遮阳系统、通风廊道。街道布局采用东南-西北走向促进自然通风，行道树选择耐高温品种并设置根部透水区。"
      }
    ]
  },
  {
    "domain": "团队协作",
    "model": [
      {
        "name": "心理安全感模型",
        "info": "通过建立团队成员间的信任环境，使成员敢于表达观点、承认错误并承担风险。应用时需主动倾听、鼓励非评判性反馈，可显著提升团队创新能力和问题解决效率。"
      },
      {
        "name": "任务互赖性框架",
        "info": "识别团队成员任务间的依赖关系，通过可视化任务流程图明确交接节点和协作要求。使用甘特图或RACI矩阵可有效预防工作重复和进度延迟问题。"
      },
      {
        "name": "冲突转化策略",
        "info": "将人际冲突转化为建设性对话的4步法：1) 区分立场与需求 2) 重构对立观点为共同挑战 3) 开发多重解决方案 4) 建立可量化的执行标准。适用于处理资源分配和决策分歧场景。"
      }
    ]
  },
  {
    "domain": "教育策略",
    "model": [
      {
        "name": "建构主义学习模型",
        "info": "强调学习者通过主动参与、社会互动和情境体验构建知识体系，教师角色从知识传授者转变为引导者。应用方法：设计基于问题/项目的学习活动，鼓励协作讨论，提供真实情境案例帮助知识迁移。"
      },
      {
        "name": "元认知策略",
        "info": "通过计划-监控-评估的循环过程管理学习，包含设定具体目标、选择策略、自我提问、记录学习日志、定期复盘等可操作步骤，适用于提升自主学习能力。"
      },
      {
        "name": "差异化教学框架",
        "info": "根据学习者准备度、兴趣特征、学习偏好三维度调整教学内容/过程/成果，具体实施包含分层任务设计、多元智能活动选项、弹性分组策略等工具方法。"
      },
      {
        "name": "形成性评估系统",
        "info": "通过课堂即时反馈(如应答器)、学习分析仪表盘、成长档案袋等工具持续收集学习证据，用于动态调整教学节奏和提供个性化介入指导。"
      },
      {
        "name": "认知负荷理论应用",
        "info": "通过分步呈现信息、整合图文元素、预训练关键概念等方式管理工作记忆负荷，具体实施包含模块化内容设计、脚手架技术、冗余信息消除等实践原则。"
      }
    ]
  },
  {
    "domain": "数字营销策略",
    "model": [
      {
        "name": "AIDA模型",
        "info": "通过四个阶段（引起注意Attention、激发兴趣Interest、创造欲望Desire、促成行动Action）引导用户完成转化路径。应用时需针对性设计内容：用视觉冲击吸引用户→展示产品独特性→强化情感共鸣→提供明确行动指令（如限时优惠）。"
      },
      {
        "name": "客户旅程地图",
        "info": "可视化用户从初次接触到最终转化的全过程，包含认知阶段、考虑阶段、决策阶段和忠诚阶段。需识别各阶段的关键触点，针对性优化内容投放、渠道选择和用户体验设计。"
      },
      {
        "name": "RACE框架",
        "info": "覆盖数字营销全周期的四环节：触达（Reach）目标受众→激发互动（Act）→建立转化（Convert）→提升用户终身价值（Engage）。需配置相应指标（如触达率、CTR、转化率、复购率）进行持续优化。"
      },
      {
        "name": "7C营销模型",
        "info": "包含内容（Content）、场景（Context）、社群（Community）、定制化（Customization）、沟通（Communication）、连接（Connection）、商业转化（Commerce）七大要素。要求各要素协同运作，例如通过用户画像实现内容个性化，利用社交裂变扩大传播。"
      }
    ]
  },
  {
    "domain": "法律论证",
    "model": [
      {
        "name": "类比推理模型",
        "info": "通过系统比较待决案件与先例案件的关键事实要素，建立相似性关联框架，运用案例要素匹配矩阵和差异权重评估表，构建具有说服力的法律论证结构。具体包含事实特征提取、相似度量化评估、区别点抗辩预判三个实施阶段。"
      },
      {
        "name": "政策检验框架",
        "info": "采用目的论分析方法，通过建立政策目标决策树，将法律条文置于社会效益、经济效率、道德伦理等多维度评估体系中。运用成本收益分析表、利益相关方影响图谱、长期效果预测模型等工具验证法律解释的合目的性。"
      },
      {
        "name": "要件解构技术",
        "info": "将法律规范分解为构成要件图谱，使用要素核查清单逐项验证案件事实的符合性。包含要件相关性分析、证据充分性评估、证明责任分配三个核心模块，配套开发动态要件权重调整算法应对复杂案件。"
      },
      {
        "name": "漏洞填补策略",
        "info": "当法律存在空白时，采用法律原则金字塔模型，通过上位原则推导、类似制度参照、比较法借鉴三维度构建解决方案。配套使用原则冲突协调矩阵和填补方案可行性评估量表确保方案的合法性。"
      },
      {
        "name": "论证强度评估",
        "info": "建立包含逻辑严密性、证据支持度、价值协调性等12个维度的论证质量评估体系，运用论证漏洞扫描清单和抗辩点预测模型，通过论证结构可视化工具进行多轮迭代优化。"
      }
    ]
  },
  {
    "domain": "运营效率优化",
    "model": [
      {
        "name": "约束理论",
        "info": "通过持续识别系统中的最弱环节（瓶颈），集中资源突破约束点，从而实现整体系统效能指数级提升的思维方法。应用步骤：1) 识别当前约束 2) 最大限度利用约束资源 3) 使非约束环节服从约束环节 4) 提升约束环节能力 5) 重复流程防止惰性成为新约束"
      },
      {
        "name": "单件流思维",
        "info": "通过最小化单批次处理量来暴露流程缺陷的改善方法。实施要点：1) 将批量生产改为单件传递 2) 建立异常停线机制 3) 采用U型产线布局 4) 培养多能工 5) 实施目视化管理，可减少90%在制品库存并提升质量响应速度"
      },
      {
        "name": "价值流分析",
        "info": "通过绘制物料与信息流动图谱识别非增值活动的工具。操作框架：1) 选定产品族 2) 现况图绘制(包括周期时间/换型时间等16项指标) 3) 未来图设计 4) 制定3P(生产准备流程)方案 5) 建立节拍时间平衡机制，可系统性消除7类浪费"
      },
      {
        "name": "自主维护体系",
        "info": "通过操作者参与设备保养提升综合效率的方法。实施阶段：1) 初期清扫 2) 发生源对策 3) 临时基准制定 4) 总点检 5) 自主点检 6) 标准化 7) 自主管理，配合可视化标签和OPL单点课程，可将设备故障率降低75%"
      },
      {
        "name": "平准化生产",
        "info": "通过均衡产品类型与数量实现稳定生产的高级排程技术。关键算法：1) 计算产品周期比率 2) 制作均衡生产箱 3) 设定循环批次 4) 混流排序(考虑工时平衡) 5) 动态调整安全库存，可减少30%产能波动损失"
      }
    ]
  },
  {
    "domain": "可持续能源设计",
    "model": [
      {
        "name": "系统思维框架",
        "info": "通过分析能源系统中各要素（发电/传输/存储/消费）的相互作用关系，建立动态反馈机制模型。重点关注能源流动效率、环境影响和经济成本的三角平衡关系。"
      },
      {
        "name": "生命周期评估模型",
        "info": "采用'从摇篮到坟墓'的评估方法，量化能源系统在原材料开采、设备制造、运营维护到报废回收的全生命周期内碳排放、资源消耗和生态影响。"
      },
      {
        "name": "多准则决策分析",
        "info": "构建包含技术可行性（能源密度/稳定性）、经济成本（LCOE平准化成本）、环境影响（碳足迹/土地使用）和社会接受度（文化适应性/就业影响）的决策矩阵进行综合评估。"
      },
      {
        "name": "弹性设计原则",
        "info": "通过分布式架构设计（微电网）、冗余备份系统（储能缓冲）、气候适应技术（极端天气防护）建立应对供需波动和外部冲击的能源系统。"
      },
      {
        "name": "利益相关者分析图谱",
        "info": "识别政府机构、能源企业、在地社区、环保组织等关键利益相关方，通过需求/影响力矩阵协调政策合规、商业利益与社会责任之间的关系。"
      }
    ]
  },
  {
    "domain": "创新扩散",
    "model": [
      {
        "name": "创新扩散理论",
        "info": "由Everett Rogers提出的经典框架，将创新传播过程分解为认知-说服-决策-实施-确认五个阶段，识别相对优势、兼容性、复杂性、可试性和可观察性五大核心要素，通过早期采用者、早期大众、晚期大众等用户分层制定传播策略。"
      },
      {
        "name": "技术采用生命周期",
        "info": "将市场接受度划分为创新者(2.5%)、早期采用者(13.5%)、早期大众(34%)、晚期大众(34%)和落后者(16%)，强调需要跨越早期采用者与早期大众之间的'死亡鸿沟'，通过完善产品完整性和建立参考案例实现市场突破。"
      },
      {
        "name": "巴斯扩散模型",
        "info": "采用微分方程量化创新传播速度，区分创新系数(外部影响)和模仿系数(内部人际影响)，通过计算临界点预测市场渗透率，适用于新产品上市时的市场预测和资源分配决策。"
      },
      {
        "name": "社会网络理论",
        "info": "分析创新传播中的网络结构特征，识别意见领袖、结构洞和弱连接的关键作用，运用中心性指标定位传播节点，通过激发跨界传播和建立传播联盟加速扩散过程。"
      }
    ]
  },
  {
    "domain": "情感智能",
    "model": [
      {
        "name": "情绪颗粒度理论",
        "info": "通过精确识别和命名具体情绪状态来增强情绪调节能力的思维框架。操作步骤：1.记录情绪触发事件 2.使用情绪轮盘工具准确定义情绪名称 3.分析该情绪对应的生理反应和行为倾向 4.制定针对性的调节策略（如深呼吸对应焦虑、运动对应烦躁）。"
      },
      {
        "name": "共情三角模型",
        "info": "构建有效共情的三个维度：认知共情（理解他人观点）、情感共情（感受他人情绪）、共情关怀（产生帮助意愿）。应用方法：在对话中主动进行视角切换练习，使用情绪标签化表述（如'听起来你很失望'），同步匹配非语言信号（语调/姿态）。"
      },
      {
        "name": "情感银行账户",
        "info": "将人际关系比作情感账户的概念模型。存款行为包括主动倾听、及时回应、兑现承诺；取款行为包括批评指责、忽视需求、违背信任。维护原则：保持5:1的积极互动比例，重大冲突后需进行专门的情感账户审计与修复。"
      },
      {
        "name": "情绪ABC理论",
        "info": "认知行为疗法核心模型：激发事件（A）通过信念系统（B）产生情绪后果（C）。应用流程：1.识别自动化负面思维 2.检验证据真实性 3.构建替代性解释 4.实施行为实验验证。包含常见认知扭曲清单（如灾难化、过度概括）及对应矫正策略。"
      },
      {
        "name": "情感粒度调节法",
        "info": "通过建立情绪-需求对应表实现精准情绪管理的技术。操作框架：1.建立情绪词典（200+情绪词库）2.绘制情绪模式地图（时间/强度/触发规律）3.制定分级应对方案（如轻度焦虑使用478呼吸法，重度焦虑启动认知重构协议）。"
      }
    ]
  },
  {
    "domain": "战略规划",
    "model": [
      {
        "name": "SWOT分析框架",
        "info": "通过系统评估组织内部优势(Strengths)与劣势(Weaknesses)，结合外部机会(Opportunities)与威胁(Threats)，形成战略决策矩阵。具体操作时需将内部因素与外部环境交叉分析，推导出SO（优势+机会）战略、WO（劣势+机会）战略、ST（优势+威胁）战略和WT（劣势+威胁）战略四类解决方案。"
      },
      {
        "name": "波特五力模型",
        "info": "用于行业竞争结构分析的工具，包含供应商议价能力、购买者议价能力、新进入者威胁、替代品威胁、同业竞争强度五个维度。通过量化评估各项力量强度，可预测行业利润率并制定防御/进攻策略，例如在供应商集中度高的行业建立垂直整合体系。"
      },
      {
        "name": "平衡计分卡",
        "info": "将战略目标转化为可执行的四维指标体系：财务维度关注股东回报，客户维度衡量市场价值主张，内部流程维度优化关键运营环节，学习成长维度建设组织能力。要求四个维度形成因果关系链，例如员工培训投入（学习成长）→流程改进（内部流程）→客户满意度提升（客户）→收入增长（财务）。"
      },
      {
        "name": "蓝海战略",
        "info": "通过价值创新同时实现差异化和低成本，创造无竞争市场空间。使用战略画布工具对比行业竞争要素，消除产业常规要素（如航空业餐食），减少过度服务要素，提升关键价值要素（如点对点直飞），创造新需求要素（如廉价航空的电子值机）。"
      },
      {
        "name": "情景规划法",
        "info": "构建2-4个基于关键不确定因素的未来情景（如技术突破/政策变化），每个情景包含完整的事件发展逻辑链。通过压力测试验证现有战略的鲁棒性，并为每个情景预置触发式应对方案，例如设立技术监测指标和预案启动阈值。"
      }
    ]
  },
  {
    "domain": "知识管理",
    "model": [
      {
        "name": "SECI模型",
        "info": "通过社会化(Socialization)、外在化(Externalization)、组合化(Combination)、内在化(Internalization)四个阶段实现隐性知识与显性知识相互转化的框架。具体应用：通过观察模仿获取隐性知识（社会化），将经验转化为可表述概念（外在化），系统化整理成知识体系（组合化），最终内化为个人能力（内在化）。"
      },
      {
        "name": "构建第二大脑",
        "info": "采用CODE法则(Capture捕获-Organize组织-Distill提炼-Express输出)构建个人知识系统。操作步骤：1) 建立跨平台信息收集机制 2) 使用PARA分类法(项目-领域-资源-归档)进行知识组织 3) 通过渐进式总结提炼知识要点 4) 建立知识复用与输出机制。"
      },
      {
        "name": "费曼知识验证法",
        "info": "通过四步验证知识掌握程度：1) 选择概念并尝试解释 2) 识别解释中的模糊点 3) 返回原始材料重新学习 4) 用类比方式简化表达。持续循环直至能用简单例子向非专业者说明复杂概念。"
      },
      {
        "name": "5W1H知识溯源法",
        "info": "对任何知识要素进行结构化分析：What(本质定义)-Why(产生原因)-Where(适用场景)-When(时间条件)-Who(相关主体)-How(应用方法)。特别适用于评估信息可信度，要求每个维度都能找到至少两个独立验证来源。"
      }
    ]
  },
  {
    "domain": "跨文化沟通",
    "model": [
      {
        "name": "霍夫斯泰德的文化维度理论",
        "info": "通过权力距离、个人主义/集体主义、男性化/女性化、不确定性规避、长期导向/短期导向、放纵/克制六个维度分析文化差异，帮助预测和解释跨文化场景中的行为模式。应用时需先定位目标文化的维度特征，再针对性调整沟通策略。"
      },
      {
        "name": "霍尔的高语境与低语境理论",
        "info": "区分高语境文化（信息隐含在情境中）与低语境文化（信息明确表达）。与高语境文化沟通需关注非言语线索、人际关系和历史背景；与低语境文化沟通应注重逻辑清晰、条款明确和直接表达。"
      },
      {
        "name": "文化智商(CQ)模型",
        "info": "包含认知CQ（理解文化差异的知识）、动机CQ（跨文化互动的意愿）、行为CQ（调整言行的能力）三个维度。提升方法包括：文化框架切换训练、文化导师制、沉浸式情境模拟等。"
      }
    ]
  },
  {
    "domain": "创业策略",
    "model": [
      {
        "name": "精益创业循环",
        "info": "通过构建(Build)-测量(Measure)-学习(Learn)的反馈循环持续验证商业假设。具体流程：快速建立最小可行产品(MVP)→收集用户行为数据→分析验证假设→迭代改进或转型(pivot)，适用于降低创业失败风险。"
      },
      {
        "name": "颠覆式创新框架",
        "info": "通过提供更简单/更便宜/更便捷的解决方案，从低端市场或新市场切入，逐步颠覆现有市场结构。实施步骤：识别被过度服务的客户群体→设计针对性价值主张→建立独立运营单元→向上层市场渗透。"
      },
      {
        "name": "增长黑客模型",
        "info": "以数据驱动的低成本增长方法论，包含获客(Acquisition)-激活(Activation)-留存(Retention)-变现(Revenue)-推荐(Referral)的AARRR漏斗。通过快速实验寻找关键增长杠杆，典型应用包括病毒系数优化、漏斗转化率提升等。"
      },
      {
        "name": "蓝海战略画布",
        "info": "通过消除(Eliminate)-减少(Reduce)-提升(Raise)-创造(Create)的四步框架重构价值曲线。工具包括战略布局图可视化竞争对手要素投入，帮助创业者跳出红海竞争，开辟未饱和的新市场空间。"
      },
      {
        "name": "产品市场匹配指数",
        "info": "Marc Andreessen提出的PMF(Product-Market Fit)验证标准：40%以上用户表示会「非常失望」如果无法继续使用你的产品。测量方法包括用户调查、NPS净推荐值、自然增长率等，达到PMF前不应大规模扩张。"
      }
    ]
  },
  {
    "domain": "数据隐私管理",
    "model": [
      {
        "name": "隐私设计框架",
        "info": "在系统或产品设计初期即嵌入隐私保护机制，通过默认隐私设置、数据最小化、端到端加密等技术手段，确保用户数据在收集/存储/传输各阶段均符合合规要求。例如根据GDPR要求，设计时需提供用户数据访问入口和删除功能。"
      },
      {
        "name": "风险评估矩阵",
        "info": "通过识别数据处理场景中的敏感元素(数据类型/使用目的/共享范围)，评估泄露可能性和影响程度，将风险划分为高/中/低三级。优先对高风险项实施控制措施，如医疗数据需进行匿名化处理并限制访问权限。"
      },
      {
        "name": "数据生命周期管控",
        "info": "针对数据采集、存储、使用、共享、销毁全流程制定管理策略。包括设置数据保留期限(如用户行为日志保留6个月自动删除)，建立访问审批日志，使用安全擦除工具确保报废设备中的数据不可恢复。"
      },
      {
        "name": "知情同意分层模型",
        "info": "将用户同意划分为核心功能必要同意(如账号注册手机号)与增值服务可选同意(如个性化推荐)，通过交互设计明确区分。必须提供随时撤回同意的途径，且核心功能不应因拒绝增值同意而受限。"
      },
      {
        "name": "去标识化技术组合",
        "info": "运用假名化(用ID替代真实信息)、泛化(将年龄转为年龄段)、差分隐私(添加统计噪声)等技术组合，在保持数据可用性的同时降低个人身份识别风险。如医疗研究中使用k-匿名保证每条记录至少有k-1条相同特征。"
      }
    ]
  }
]
